traad/__init__.py
traad/app.py
traad/bottle.py
traad/compat.py
traad/handlers.py
traad/plugin.py
traad/routes.py
traad/server.py
traad/state.py
traad/test.py
traad/trace.py
traad/version.py
traad/rope/__init__.py
traad/rope/auto_import.py
traad/rope/autoimport.py
traad/rope/change_signature.py
traad/rope/code_assist.py
traad/rope/codeassist.py
traad/rope/extract.py
traad/rope/findit.py
traad/rope/history.py
traad/rope/imports.py
traad/rope/importutil.py
traad/rope/inline.py
traad/rope/log.py
traad/rope/move.py
traad/rope/project.py
traad/rope/rename.py
traad/rope/thing_at.py
traad/rope/validate.py
traad/rope/workspace.py
traad-3.2.0.dist-info/LICENSE.txt
traad-3.2.0.dist-info/METADATA
traad-3.2.0.dist-info/WHEEL
traad-3.2.0.dist-info/entry_points.txt
traad-3.2.0.dist-info/top_level.txt
traad-3.2.0.dist-info/RECORD
