Metadata-Version: 2.1
Name: traad
Version: 3.2.0
Summary: A JSON+HTTP server for the rope Python refactoring library.
Home-page: http://github.com/abingham/traad
Author: Austin Bingham
Author-email: austin.bingham@gmail.com
License: MIT
Keywords: refactoring
Platform: UNKNOWN
Requires-Dist: rope
Requires-Dist: ultan
Provides-Extra: dev
Requires-Dist: twine; extra == 'dev'
Requires-Dist: wheel; extra == 'dev'
Provides-Extra: test
Requires-Dist: pytest; extra == 'test'
Requires-Dist: tox; extra == 'test'
Requires-Dist: webtest; extra == 'test'
